openclio/__init__.py
openclio/openclio.py
openclio/utils/__init__.py
openclio/utils/utils.py
openclio-0.3.dist-info/LICENSE
openclio-0.3.dist-info/METADATA
openclio-0.3.dist-info/WHEEL
openclio-0.3.dist-info/entry_points.txt
openclio-0.3.dist-info/top_level.txt
openclio-0.3.dist-info/RECORD
