Metadata-Version: 2.1
Name: openclio
Version: 0.3
Summary: OpenCL Input/Output
Home-page: https://github.com/zehanort/openclio
Author: Sotiris Niarchos
Author-email: sot.niarchos@gmail.com
License: MIT
Download-URL: https://github.com/zehanort/openclio/releases
Platform: UNKNOWN
Classifier: Development Status :: 3 - Alpha
Classifier: Intended Audience :: Developers
Classifier: Intended Audience :: Other Audience
Classifier: Intended Audience :: Science/Research
Classifier: License :: OSI Approved :: MIT License
Classifier: Operating System :: OS Independent
Classifier: Natural Language :: English
Classifier: Programming Language :: Python
Classifier: Programming Language :: Python :: 3 :: Only
Classifier: Topic :: Software Development :: Libraries :: Python Modules
Classifier: Topic :: Utilities
Requires-Python: >=3.6
License-File: LICENSE
Requires-Dist: llvmlite (>=0.36.0)
Requires-Dist: pandas (>=1.2.4)
Requires-Dist: tabulate (>=0.8.9)
